creed/__init__.py
creed/python.ico
creed-0.2.3.dist-info/LICENSE
creed-0.2.3.dist-info/METADATA
creed-0.2.3.dist-info/WHEEL
creed-0.2.3.dist-info/top_level.txt
creed-0.2.3.dist-info/RECORD
