Metadata-Version: 2.1
Name: creed
Version: 0.2.3
Summary: the one and only cross-platform Toaster/Notification in python
Home-page: https://github.com/yusuf8ahmed/Creed
Author: Yusuf Ahmed
Author-email: yusufahmed172@gmail.com
License: UNKNOWN
Platform: UNKNOWN
Classifier: Development Status :: 3 - Alpha
Classifier: Programming Language :: Python :: 3
Classifier: License :: OSI Approved :: MIT License
Classifier: Operating System :: OS Independent
Requires-Python: >=3.6
Requires-Dist: pypiwin32 (==223)
Requires-Dist: win10toast (==0.9)
